QPandaLitePy.cpython-311-x86_64-linux-gnu.so
qpandalite/__init__.py
qpandalite/__version__.py
qpandalite/analyzer/__init__.py
qpandalite/analyzer/expectation.py
qpandalite/analyzer/result_adapter.py
qpandalite/circuit_builder/__init__.py
qpandalite/circuit_builder/qcircuit.py
qpandalite/originir/__init__.py
qpandalite/originir/originir_base_parser.py
qpandalite/originir/originir_line_parser.py
qpandalite/originir/originir_spec.py
qpandalite/originir/random_originir.py
qpandalite/qasm/__init__.py
qpandalite/qasm/exceptions.py
qpandalite/qasm/qasm_base_parser.py
qpandalite/qasm/qasm_line_parser.py
qpandalite/qasm/qasm_spec.py
qpandalite/qasm/random_qasm.py
qpandalite/qasm/translate_qasm2_oir.py
qpandalite/qcloud_config/__init__.py
qpandalite/qcloud_config/ibm_online_config.py
qpandalite/qcloud_config/originq_cloud_config.py
qpandalite/qcloud_config/originq_online_config.py
qpandalite/qcloud_config/quafu_online_config.py
qpandalite/simulator/QPandaLitePy.pyi
qpandalite/simulator/__init__.py
qpandalite/simulator/base_simulator.py
qpandalite/simulator/error_model.py
qpandalite/simulator/get_backend.py
qpandalite/simulator/opcode_simulator.py
qpandalite/simulator/originir_simulator.py
qpandalite/simulator/qasm_simulator.py
qpandalite/simulator/qutip_sim_impl.py
qpandalite/task/__init__.py
qpandalite/task/task_utils.py
qpandalite/task/ibm/__init__.py
qpandalite/task/ibm/task.py
qpandalite/task/origin_qcloud/__init__.py
qpandalite/task/origin_qcloud/task.py
qpandalite/task/originq/__init__.py
qpandalite/task/originq/task.py
qpandalite/task/originq_dummy/__init__.py
qpandalite/task/originq_dummy/task.py
qpandalite/task/platform_template/__init__.py
qpandalite/task/platform_template/task.py
qpandalite/task/quafu/__init__.py
qpandalite/task/quafu/task.py
qpandalite/test/QASMBench.pkl
qpandalite/test/__init__.py
qpandalite/test/_utils.py
qpandalite/test/test_QASMBench.py
qpandalite/test/test_demos.py
qpandalite-0.2.5.dist-info/LICENSE
qpandalite-0.2.5.dist-info/METADATA
qpandalite-0.2.5.dist-info/WHEEL
qpandalite-0.2.5.dist-info/top_level.txt
qpandalite-0.2.5.dist-info/RECORD
