Metadata-Version: 2.2
Name: qpandalite
Version: 0.2.5
Summary: QPanda-Lite. A python-native version for pyqpanda. Simple, easy, and transparent.
Author: Agony
Author-email: chenzhaoyun@iai.ustc.edu.cn
Project-URL: Source Code, https://github.com/Agony5757/QPanda-Lite.git
Classifier: Development Status :: 5 - Production/Stable
Classifier: Intended Audience :: Science/Research
Classifier: Intended Audience :: Developers
Classifier: License :: OSI Approved :: Apache Software License
Classifier: Programming Language :: C++
Classifier: Programming Language :: Python
Classifier: Programming Language :: Python :: 3
Classifier: Programming Language :: Python :: 3.8
Classifier: Programming Language :: Python :: 3.9
Classifier: Programming Language :: Python :: 3.10
Classifier: Programming Language :: Python :: 3.11
Classifier: Programming Language :: Python :: 3.12
Classifier: Programming Language :: Python :: 3 :: Only
Classifier: Topic :: Scientific/Engineering :: Artificial Intelligence
Classifier: Operating System :: Microsoft :: Windows
Classifier: Operating System :: POSIX
Classifier: Operating System :: Unix
Requires-Python: >=3.8
License-File: LICENSE
Requires-Dist: numpy
Requires-Dist: requests
Requires-Dist: pandas
Requires-Dist: seaborn
Requires-Dist: matplotlib
Requires-Dist: rb_generator
Requires-Dist: pybind11-stubgen
Requires-Dist: qiskit
Requires-Dist: qiskit-aer
Requires-Dist: qutip
Requires-Dist: qutip-qip
Dynamic: author
Dynamic: author-email
Dynamic: classifier
Dynamic: description
Dynamic: description-content-type
Dynamic: project-url
Dynamic: requires-dist
Dynamic: requires-python
Dynamic: summary
